dbgress/__init__.py
dbgress/cli.py
dbgress/compare.py
dbgress/export.py
dbgress/files.py
dbgress/load.py
dbgress/meta.py
dbgress/transfer.py
dbgress/utils.py
dbgress-0.1.4.dist-info/METADATA
dbgress-0.1.4.dist-info/WHEEL
dbgress-0.1.4.dist-info/entry_points.txt
dbgress-0.1.4.dist-info/top_level.txt
dbgress-0.1.4.dist-info/RECORD
