Metadata-Version: 2.1
Name: dbgress
Version: 0.1.4
Summary: Database incremental exports, transfers, imports, ETL, creation / management
Author-email: Dan Kelleher <kelleherjdan@gmail.com>
License: MIT
Classifier: Programming Language :: Python
Classifier: Programming Language :: Python :: 3
Classifier: Topic :: Software Development
Classifier: Topic :: Software Development :: Libraries
Classifier: Topic :: Software Development :: Libraries :: Python Modules
Requires-Dist: fileflows
Requires-Dist: sqlalchemy >=2.0.0
Requires-Dist: quicklogs
Requires-Dist: dynamic-imports
Requires-Dist: click
Requires-Dist: xxhash
Requires-Dist: tqdm
Requires-Dist: pydantic >=2.0.0
Requires-Dist: cytoolz
Provides-Extra: all
Requires-Dist: drivers ; extra == 'all'
Requires-Dist: transfer ; extra == 'all'
Provides-Extra: dev
Requires-Dist: black ; extra == 'dev'
Requires-Dist: pytest ; extra == 'dev'
Requires-Dist: pytest-asyncio ; extra == 'dev'
Requires-Dist: faker ; extra == 'dev'
Requires-Dist: python-dotenv ; extra == 'dev'
Provides-Extra: drivers
Requires-Dist: psycopg[c] ; extra == 'drivers'
Requires-Dist: asyncpg ; extra == 'drivers'
Provides-Extra: transfer
Requires-Dist: connectorx ; extra == 'transfer'
Requires-Dist: pandas ; extra == 'transfer'
